Workbook

Sheet Publication Status Tracker NIE
F1: PLANNING & COLLABORATION (new) | G1: EXISTING COLUMNS (cleaned & standardised) | I1: PLANNING & COLLABORATION (new) | J1: EXISTING COLUMNS (cleaned & standardised) | M1: QUALITY & INDEXING — HIGH PRIORITY (new) | O1: EXISTING COLUMNS (cleaned & standardised) | Q1: QUALITY & INDEXING — HIGH PRIORITY (new) | S1: PLANNING & COLLABORATION (new)
A2: Title of the Paper | B2: Author(s) List | C2: Department | D2: Campus | E2: Corresponding Author | F2: Faculty Designation | G2: Status | H2: Start Date | I2: Submission Date | J2: Acceptance Date (Probable) | K2: Elapsed Days | L2: Publication Type | M2: Journal / Conference Name | N2: Impact Factor (IF) | O2: Scopus Quartile | P2: Web of Science (SCI/SCIE/ESCI) | Q2: DOI / URL | R2: Citation Count | S2: Citation Updated On | T2: Target Journal / Conference | U2: Rejection / Revision Count | V2: Research Area / Keywords | W2: Funding / Grant Title | X2: Funding Agency | Y2: Grant Amount (Rs. Lakhs) | Z2: External Collaborators | AA2: Student Co-authors | AB2: PhD Thesis Link | AC2: Review Notes / Comments
A3: Machine Learning for Bearing Health Monitoring: A Performance Evaluation with Vibration Data | B3: Prasanta Kumar Samal, Imran M Jamadar | C3: MECH | D3: South | E3: Ptrasanta Kumar Samal | F3: Assistant Professor | G3: Under Review | H3: 45736 | I3: 21/11/2025 | J3: 46203 | K3: =IF(AND(H3<>"",J3<>""),J3-H3,"") -> 467 | L3: Journal Article | N3: 0.71 | O3: Q3 | P3: Yes | U3: R2 | V3: Condition Monitoring of Bearing using Machine Learning | X3: None | AA3: None
A4: Synergistic Effects of Wood Filler – Glass/Carbon Fibers on the Tribological Behavior of Polypropylene Hybrid Composites | B4: H. V. Divya, T. P. Jeevan, T. G. Yashas Gowda & A. Anand | C4: MECH | D4: South | E4: Anand A | F4: Assistant Professor | G4: Published | H4: 45597 | J4: 45723 | K4: =IF(AND(H4<>"",J4<>""),J4-H4,"") -> 126 | L4: Journal Article | M4: Journal | O4: Q1 | P4: Yes
A5: Exploring the integration of renewable energy sources for sustainable charging infrastructure in electric vehicles | B5: R.A. Priya, Subrata Jana, Sri Harsha Grandhi, Saroj Kumar Nanda, Pappula Sampath Kumar, V. Vikram Athreya | C5: MECH | D5: South | E5: Vikram Athreya V | F5: Assistant Professor | G5: Published | H5: 45334 | I5: 22/01/2025 | J5: 45740 | K5: =IF(AND(H5<>"",J5<>""),J5-H5,"") -> 406 | L5: Book Chapter | M5: Hybrid and Advanced Technologies | O5: Q4 | P5: No | Q5: http://dx.doi.org/10.1201/9781003559139-52 | V5: EVs charging | X5: None
A6: Simulation and Optimisation of Automated Robot Workstation of Car Body-in-White using Process Simulate | B6: Vikram Athreya V, Sunil Gaekwad, Sharath Chandra N, Sanjay Gowda H M | C6: MECH | D6: South | E6: Vikram Athreya V | F6: Assistant Professor | G6: Published | H6: 45366 | I6: 45545 | J6: 45664 | K6: =IF(AND(H6<>"",J6<>""),J6-H6,"") -> 298 | L6: Conference Paper | M6: Intelligent Control, Robotics, and Industrial Automation: Proceedings of International Conference, RCAAI 2024 | O6: Q4 | P6: No | Q6: https://doi.org/10.1007/978-981-95-2901-8_3 | V6: Automation system for Automotive body manufacturing | X6: None
A7: Development of CNC Thread Milling Machine with Hobbing Head | B7: Sathyanidhi Acharya H R, Vikram Athreya V | C7: MECH | D7: South | E7: Vikram Athreya V | F7: Assistant Professor | G7: Published | H7: 45453 | J7: 45669 | K7: =IF(AND(H7<>"",J7<>""),J7-H7,"") -> 216 | L7: Conference Paper | O7: Q4
A8: Morphological Analysis of FDM parts subjected to Surface Treatment | B8: Sunil Gaekwad, Sharath Chandra N, Vikram Athreya V | C8: MECH | D8: South | E8: Vikram Athreya V | F8: Assistant Professor | G8: Published | H8: 45733 | J8: 45901 | K8: =IF(AND(H8<>"",J8<>""),J8-H8,"") -> 168 | L8: Journal Article | O8: Q1 | P8: Yes
A9: Water Salinity Concentration Detection using Photonic Crystal Sensor | B9: Shreya H C, Meena Y R, Preeta Sharan, and Sharath Chandra N | C9: MECH | D9: South | E9: Shreya H C | G9: Accepted | H9: 45658 | J9: 45708 | K9: =IF(AND(H9<>"",J9<>""),J9-H9,"") -> 50 | L9: Conference Paper | O9: Q4
A10: Multi-Level Smart Grid Using Naïve Bayes Classifier for Renewable Energy Integration | B10: Pavithra Goravi Sukumar, Balachandra parameshwariah, A. M. Prasad, Sharmila Nagaraju, Mallikarjunaswamy Srikantaswamy, Sharath Chandra N | C10: MECH | D10: South | E10: Pavithra Goravi Sukumar | G10: Accepted | H10: 45658 | J10: 45708 | K10: =IF(AND(H10<>"",J10<>""),J10-H10,"") -> 50 | L10: Journal Article | O10: Q3
A11: AI-Driven Intelligent Power Management for Optimized Renewable Energy Utilization | B11: Pavithra Goravi Sukumar, Chandana Chikkasiddaiah and Mallikarjunaswamy Srikantaswamy, Sharmila Nagaraju, Balachandra parameshwariah, Sharath Chandra N | C11: MECH | D11: South | E11: Pavithra Goravi Sukumar | G11: Accepted | H11: 45659 | J11: 45708 | K11: =IF(AND(H11<>"",J11<>""),J11-H11,"") -> 49 | L11: Journal Article | O11: Q2
A12: Prototype for Stress-based Viral Fever Prediction | B12: Anand Srivatsa, Fida Fareesha, Lekhana G, chandanashree yk, gowthami v | C12: ECE | D12: South | E12: Dr. Anand srivatsa | F12: Associate Professor | G12: Under Review | H12: 45895 | I12: 46003 | J12: 45931 | K12: =IF(AND(H12<>"",J12<>""),J12-H12,"") -> 36 | L12: Journal Article | M12: Journal (TASET) lanshscience.com
A13: Online Inspection of Sprocket using Cognex Vision Sensor IS2000 | B13: Dr. Prakash K R, VinodKumar H P, Ravalnath Bhat | C13: MECH | D13: South | E13: VinodKumar H P | G13: Submitted | H13: 45730 | J13: 45931 | K13: =IF(AND(H13<>"",J13<>""),J13-H13,"") -> 201 | L13: Conference Paper | O13: Q4
A14: A Novel Suction Cup System to Open Cardboard Box Corrugated Partition for Packing | B14: Hruthik P N, VinodKumar H P | C14: MECH | D14: South | E14: VinodKumar H P | G14: Submitted | H14: 45681 | J14: 45870 | K14: =IF(AND(H14<>"",J14<>""),J14-H14,"") -> 189 | L14: Conference Paper | O14: Q4
A15: Residual vibrations control of a 3D printed lightweight single link flexible manipulator. | B15: Imran M Jamadar, allwin yesuvadian R, Prasanta Kumar Samal, VinodKumar H P, Anand A | C15: MECH | D15: South | E15: Imran M Jamadar | F15: Professor | G15: Accepted | H15: 45748 | J15: 45931 | K15: =IF(AND(H15<>"",J15<>""),J15-H15,"") -> 183 | L15: Journal Article | M15: Sigma Journal of Engineering and Natural Sciences | N15: 0.6 | O15: Q4 | P15: Yes | Q15: 10.14744/sigma.2025.00167 | R15: 0 | S15: 31-03-2026 | U15: 1 | V15: Vibration control, 3D printing, PLC control, ANSYS | W15: State University Research Excellence | X15: SERB | Y15: 17.5 | AA15: PG Only | AB15: No
A16: A Study of Impact Toughness Behavior and High Cycle Fatigue Properties of Al-Li 8090 Alloy Processed by Cryorolling and Post-Deformation Annealing | B16: Yogesha K K, Subham Thapliyal, Amit Joshi, Saurabh Gairola, GK Kalavathi, MG Vasundhara, B Muralidhara, | C16: MECH | D16: South | E16: Amit Joshi | G16: Published | H16: 45543 | J16: 45714 | K16: =IF(AND(H16<>"",J16<>""),J16-H16,"") -> 171 | L16: Journal Article | O16: Q3
A17: Fatigue and Fracture Behaviour of 5052 Al Alloy Processed through Combined Severe Plastic Deformation Method | B17: Yogesha K K, Amit Joshi , Saurabh Gairola, R. Jayaganthan, G. M. Owolabi. | C17: MECH | D17: South | E17: Amit Joshi | G17: Under Review | H17: 45689 | J17: 45869 | K17: =IF(AND(H17<>"",J17<>""),J17-H17,"") -> 180 | L17: Book Chapter | O17: Q4
A18: "Sustainable Performance Enhancement of Polypropylene Composites Using Areca Husk Powder Reinforcement: A Comprehensive Analysis" | B18: Yogesha K K, Chandan M. | C18: MECH | D18: South | E18: Yogesha K K | F18: Professor | G18: Under Review | H18: 45722 | J18: 45900 | K18: =IF(AND(H18<>"",J18<>""),J18-H18,"") -> 178 | L18: Journal Article | O18: Q1
A19: "Optimizing Areca Husk Powder-Polypropylene Composites using Fuzzy AHP and TOPSIS" | B19: Yogesha K K, Chandan M | C19: MECH | D19: South | E19: Yogesha K K | F19: Professor | G19: Under Review | H19: 45748 | J19: 45930 | K19: =IF(AND(H19<>"",J19<>""),J19-H19,"") -> 182 | L19: Journal Article | O19: Q3
A20: A Comparative Analysis of Machine Learning Algorithms for Fault Classification in Cylindrical Roller Bearings | B20: Prasanta Kumar Samal, Imran M Jamadar | C20: MECH | D20: South | E20: Prasanta Kumar Samal | F20: Assistant Professor | G20: Published | H20: 45615 | J20: 45991 | K20: =IF(AND(H20<>"",J20<>""),J20-H20,"") -> 376 | L20: Journal Article | M20: FME Transactions | N20: 1.2 | O20: Q2 | P20: Yes | Q20: doi: 10.5937/fme2504681K | V20: Vibration based Condition monitoring of Cylinderical Bearing using machine learning | X20: None | AA20: PG Only
A21: Real-Time Autonomous Driving: A Unified Single-Stage Multi-Task Network Architecture | B21: Dr. S. RAGHAVENDRA,Dr. RAJALEKSHMI KISHORE, Mr. S. K. ABHILASH,Miss VENU MADHAV NOOKALA,Dr. MANISH VARUN YADAV | C21: ECE | D21: South | E21: Rajalekshmi Kishore | F21: Associate Professor | G21: Published | H21: 45817 | I21: 45721 | J21: 45868 | K21: =IF(AND(H21<>"",J21<>""),J21-H21,"") -> 51 | L21: Journal Article | M21: IEEE Access (Journal) | O21: Q1 | P21: Yes | Q21: Digital Object Identifier 10.1109/ACCESS.2025.3572107 | R21: 0 | AA21: None | AB21: No | AC21: https://ieeexplore.ieee.org/stamp/stamp.jsp?tp=&arnumber=11008573 Note: This journal article was published in collobaration with Manipal Institute of Technology , Manipal
A22: Wireless Vision: Human Object Detection Through Obstacles | B22: Rohit Kumar, Rajiv Chaura Priyansi , Aloy Anuja Mary and Rajalekshmi Kishore | C22: ECE | D22: South | E22: Rajalekshmi Kishore | F22: Associate Professor | G22: Published | H22: 45719 | J22: 45838 | K22: =IF(AND(H22<>"",J22<>""),J22-H22,"") -> 119 | L22: Conference Paper | M22: Proceedings of the 2025 International Conference on Advanced Research in Electronics and Communication Systems (ICARECS-2025) | O22: Q2 | P22: No | Q22: 10.2991/978-94-6463-754-0_43
A23: In-silico studies of 3-tert-butyl-7-[2-phenyl ethenyl]-4H-[1,3,4]thiadiazolo [2,3-c][1,2,4] triazin-4-one as a Potential SARS-CoV-2 Inhibitor: Insights from an experimental and computational approach | B23: Chandra, Lohith T.N., B. H. Gayathri, Mehran Feizi-Dehnayebi, Karthik V, Shamantha Kumar, Divya, M.A. Sridhar, M. Mahendra, Ghodsi Mohammadi Ziarani | C23: PHY | D23: South | E23: B. H. Gayathri | G23: Published | H23: 45588 | J23: 45709 | K23: =IF(AND(H23<>"",J23<>""),J23-H23,"") -> 121 | L23: Journal Article | O23: Q2 | P23: Yes
A24: Growth, and characterization of the nonlinear optical crystal 2’, 3’‑Di‑O‑acetyl‑5’‑deoxy‑5‑fluoro‑N4‑ (pentyloxycarbonyl) cytidine: structural, optical, thermal, electrical, and molecular docking studies | B24: Dhanushchandraguru H M, Hemaraju B C, Chandra, Vinay Kumar D C, Vinayakprasanna N Hegde , Manju V V, Deeksha K B and Yashas Gowda T G | C24: PHY | D24: South | E24: Hemaraju B C | G24: Published | H24: 45878 | J24: 45900 | K24: =IF(AND(H24<>"",J24<>""),J24-H24,"") -> 22 | L24: Journal Article | O24: Q2 | P24: Yes
A25: Eco-friendly Synthesis of BiVO4 Nanoparticles from Ipomoea Campanulata Leaf Extracts: Advances in Photocatalysis and Electrochemical Sensing | B25: Sunil Kumar K C, Chandra, Lakshmi Ranganatha V, Shivaganga G S, Soundarya T L, Nagaraju G, Mallikarjunaswamy C | C25: PHY | D25: South | E25: Chandra | G25: Published | H25: 45709 | J25: 45869 | K25: =IF(AND(H25<>"",J25<>""),J25-H25,"") -> 160 | L25: Journal Article | O25: Q2 | P25: Yes
A26: Comprehensive structural, electronic, and in-silico characterization of 1-phenyl-5-(m-tolyl)-1H-tetrazole as a potential steroidogenic factor-1 (SF-1) inhibitor candidate | B26: H.M. Dhanushchandraguru, B.C. Hemaraju, Chandra Vinay Kumar D C, B.S. Chethan, P. Akhileshwari, R. Preetham , M.P. Sadashiva | C26: PHY | D26: South | E26: B.C. Hemaraju | G26: Published | H26: 45903 | J26: 45900 | K26: =IF(AND(H26<>"",J26<>""),J26-H26,"") -> -3 | L26: Journal Article | O26: Q2 | P26: Yes
A27: Adaptability and Performance of WiNoC AcrossDifferent Mesh Sizes | B27: Shruthi R, Shashidhara H R, Manju Rajan, Bhargavi V, Anagha M A, Sagar D K | C27: ECE | D27: South | E27: Shruthi R | G27: Under Review | H27: 45731 | J27: 45930 | K27: =IF(AND(H27<>"",J27<>""),J27-H27,"") -> 199 | L27: Journal Article | O27: Q2
A28: Organic fluorine (C–F⋯F–C) mediated intermolecular interactions in (E)-3-(2,6-difluorophenyl)-1-(4-nitrophenyl)prop‐2-en-1-one: An intuition from an experimental and computational studies | B28: Lohith T.N, Sanjeeva S., Neetha S., Kishorkumar Sindogi, Mohd Sajid Ali, Rajiv Patel | C28: PHY | D28: South | E28: Dr. Lohith T. N. | G28: Published | H28: 45688 | J28: 45744 | K28: =IF(AND(H28<>"",J28<>""),J28-H28,"") -> 56 | L28: Journal Article | O28: Q2 | P28: Yes
A29: Structural elucidation, Hirshfeld surface analysis, DFT, and molecular docking studies of puckered compound: (6aS,12aR)-9-bromo-7,7-dimethyl-docking studies of puckered compound: (6aS,12aR)-9-bromo-7,7-dimethyl-6a,7,12,12a-tetrahydro-6H,13H-thiochromeno[3′,4′:5,6]thiopyrano[4,3-b]quinoline | B29: Anindita Bhattacharjee, Subram anya Hegde, Abdul Majeed Kurumbala, Vinay Kumar D. C., Nagarajaiah Honnappa, Mohd Sajid Ali, T. N. Lohith, M. B. Madhus udana Reddy | C29: PHY | D29: South | E29: Dr. Lohith T. N. | G29: Published | H29: 45666 | J29: 45736 | K29: =IF(AND(H29<>"",J29<>""),J29-H29,"") -> 70 | L29: Journal Article | O29: Q2 | P29: Yes
A30: Discovery of novel 1,2,3-Triazole hybrids derivatives as vasorelaxant agents: Molecular structure, Hirshfield surface, in-vivo and in-silico investigation by molecular docking simulation | B30: Yassine Rhazi, Ismail Bouadid, Mohamed Eddouks, Asmae Nakkabi, Usama Raza, Lohith T. N., Noemi Deak, Albert Soran, Mohamed El Yazidi, Marwa Alaqarbeh, Abdessamad Tounsi, Mohamed Anouar Harrad | C30: PHY | D30: South | E30: Mohamed Anouar Harrad | G30: Published | H30: 45665 | J30: 45729 | K30: =IF(AND(H30<>"",J30<>""),J30-H30,"") -> 64 | L30: Journal Article | O30: Q1 | P30: Yes
A31: Exploration of piperazine‐citral sulfonyl derivatives: antibacterial and in‐silico studies against methicillin‐resistant Staphylococcus aureus | B31: K. Nirusha, H. S. Nagendra Prasad, T. N. Lohith, P. Saravanan, L. Mallesha, A. P. Anand | C31: PHY | D31: South | E31: Nagendra Prasad H.S. | G31: Published | H31: 45646 | J31: 45700 | K31: =IF(AND(H31<>"",J31<>""),J31-H31,"") -> 54 | L31: Journal Article | O31: Q2 | P31: Yes
A32: Probing the Biological Activity of Isatin Derivatives Against Human Lung Cancer A549 Cells: Cytotoxicity, CT-DNA/BSA Binding, DFT/TD-DFT, Topology, ADME-Tox, Docking and Dynamic Simulations | B32: Ghodsi Mohammadi Ziarani, T.N. Lohith, Somayyeh Ghareghomi, Zahra Panahande, Majid Farsadrooh, Maryam Majidinia | C32: PHY | D32: South | E32: Mehran Feizi-Dehnayebi | G32: Published | H32: 45653 | J32: 45750 | K32: =IF(AND(H32<>"",J32<>""),J32-H32,"") -> 97 | L32: Journal Article | O32: Q1 | P32: Yes
A33: Interplay of weak intermolecular interactions (C-H⋅⋅⋅N and C-H⋅⋅⋅π) in pyrazole derivative: Crystal structure, Hirshfeld surface, DFT and in silico studies | B33: Madalambika, Lohith T. N., Neetha S, Vivek Hamse Kameshwar, Kothanahally S. Sharath Kumar, Mohd Sajid Ali, Hamad A. Al-Lohedan | C33: PHY | D33: South | E33: Dr. Lohith T. N. | G33: Revision Required | H33: 45750 | J33: 45807 | K33: =IF(AND(H33<>"",J33<>""),J33-H33,"") -> 57 | L33: Journal Article | O33: Q2 | P33: Yes
A34: Design, Synthesis, Molecular Docking, DFT Analysis, and Antifungal Evaluation of Novel different 1-((2-chlorophenyl)diphenylmethyl Analogues | B34: Shital Khinde, Rajesh Kancherla, H. Nagarajaiah, Lohith T. N., Perwez Alam | C34: PHY | D34: South | E34: Santosh Chhajed | G34: Under Review | H34: 45745 | J34: 45807 | K34: =IF(AND(H34<>"",J34<>""),J34-H34,"") -> 62 | L34: Journal Article | O34: Q2 | P34: Yes
A35: Probing the intermolecular interactions, binding affinity, charge density distribution of N-(3-chlorophenyl)-2-cyanoacetamide (NCPC) against Alzheimer’s disease: Insights of experimental and computational techniques | B35: Vinay Kumar D C., Nagaraja N., Shivaprasad C. M., Mohd Sajid Ali, Chethan B. S., Lohith T. N. | C35: PHY | D35: South | E35: Dr. Lohith T. N. | G35: Published | H35: 45743 | J35: 45838 | K35: =IF(AND(H35<>"",J35<>""),J35-H35,"") -> 95 | L35: Journal Article | O35: Q1 | P35: Yes
A36: Unveiling the structural and theoretical properties of 6-(2-fluoro-3-methylpyridin-4-yl)-2-(4-methoxyphenyl)-N-phenylquinoline-4-carboxamide compound as Sonic Hedgehog protein inhibitor: Synthesis, SCXRD, HSA, DFT, Docking and ADMET studies | B36: V Shalini, Vinay Kumar D C, Darshini Gowda, B. S Chethan, K. B Harsha, S. M Rajesh, K. S Rangappa | C36: PHY | D36: South | E36: K. S Rangappa | G36: Published | H36: 45632 | J36: 45680 | K36: =IF(AND(H36<>"",J36<>""),J36-H36,"") -> 48 | L36: Journal Article | O36: Q2
A37: A comprehensive investigation of 4-(4-chlorophenyl)-3-methyl-6,7,8,9-tetrahydroisoxazolo[5,4-b]quinolin-5(4H)-one as potential anticancer agent: Insights from computational and experimental results through crystal structure analysis | B37: Darshini Gowda, Vinay Kumar D C, Byresh Gowda, B.S. Chethan, K.B. Harsha, V. Shalini, M.S. Sudhanva, R. Shobith, K.S. Rangappa | C37: PHY | D37: South | E37: K.S. Rangappa | G37: Published | H37: 45477 | J37: 45676 | K37: =IF(AND(H37<>"",J37<>""),J37-H37,"") -> 199 | L37: Journal Article | O37: Q2
A38: Design and Characterization of Novel Isatin Derivatives: Insights into Crystal Structure, Intermolecular Interactions, and DFT Analysis | B38: Kishor Prasad S. Chethan B. S., Vinay Kumar D C, Pruthviraj K, Kenchanna S, Lokanath N. K. Manjunatha K and Sunil, K | C38: PHY | D38: South | E38: Sunil, K | G38: Published | H38: 45740 | J38: 45870 | K38: =IF(AND(H38<>"",J38<>""),J38-H38,"") -> 130 | L38: Journal Article | O38: Q2
A39: Structural analysis and computational studies of cyclopropane derivative as an anti- Alzheimer’s agent: Investigation of interactions by X-ray crystallography, DFT, molecular docking, and ADMET approaches | B39: S. M. Rajesh, Vinay Kumar D C, V. Shalini, K. B. Harsha, Darshini Gowda, K. S. Rangappa | C39: PHY | D39: South | E39: K. S. Rangappa | G39: Published | H39: 45730 | J39: 45788 | K39: =IF(AND(H39<>"",J39<>""),J39-H39,"") -> 58 | L39: Journal Article | O39: Q2 | P39: Yes
A40: Computational Design and Synthesis of Novel Acyl Hydrazone Derivatives Targeting Pyruvate Dehydrogenase Complex as Potent Antibacterial Agents Against E. coli | B40: Rashmi Shivakumar., Narendra Kumar, H. K., Narasimha M Beeraka., Vinay Kumar D C., Rangappa K. S., Ibrahim F. Rehan., Frantiˇsek Zigo., and Basappa Basappa. | C40: PHY | D40: South | E40: Basappa Basappa | G40: Revision Required | H40: 45719 | J40: 45808 | K40: =IF(AND(H40<>"",J40<>""),J40-H40,"") -> 89 | L40: Journal Article | O40: Q4
A41: Estimation of Negative Pore Water Pressure of Clay Sand Mixtures | B41: Jyothi D N, H S Prasanna, Unnam Anil | C41: CIVIL | D41: South | E41: Jyothi D N | G41: Accepted | H41: 45412 | J41: 45748 | K41: =IF(AND(H41<>"",J41<>""),J41-H41,"") -> 336 | L41: Book Chapter | O41: Q3
A42: SHRINKAGE LIMIT OF COMPACTED PLAIN AND FIBRE REINFORCED EXPANSIVE SOILS PRE AND POST CONSOLIDATION | B42: Unnam Anil, HS Prasanna, Jyothi D N | C42: CIVIL | D42: South | E42: Unnam Anil | G42: Accepted | H42: 45412 | J42: 45748 | K42: =IF(AND(H42<>"",J42<>""),J42-H42,"") -> 336 | L42: Book Chapter | O42: Q3
A43: A COMPARATIVE STUDY OF ESTIMATION OF SETTLEMENT OF FOOTINGS ON NON-PLASTIC SOIL USING FIELD TEST DATA | B43: H S Prasanna, Shruthi A N, Unnam Anil, Y M Manjunath | C43: CIVIL | D43: South | E43: H S Prasanna | G43: Accepted | H43: 45412 | J43: 45748 | K43: =IF(AND(H43<>"",J43<>""),J43-H43,"") -> 336 | L43: Book Chapter | O43: Q3
A44: Heat Retentivity of Non-plastic and Low plastic soils | B44: H S Prasanna, Vinay kumar K B, Satish HM, Preetham S Patel, Thilak V | C44: CIVIL | D44: South | E44: Vinay Kumar K B | G44: Accepted | H44: 45412 | J44: 45748 | K44: =IF(AND(H44<>"",J44<>""),J44-H44,"") -> 336 | L44: Book Chapter | O44: Q3
A45: Dual Adaptive Kalman Filtering Algorithm for Collaborative Assessment of Soh, Soc and Sop of Lithium-Ion Batteries Based on Electric Buses | B45: Mrs Reshma P, Dr V Joshi Manohar | C45: EEE | D45: South | E45: Mrs Reshma P | G45: Under Review | H45: 45676 | J45: 45869 | K45: =IF(AND(H45<>"",J45<>""),J45-H45,"") -> 193 | L45: Journal Article | P45: Yes
A46: Investigation of Viscosity and Tribological Characteristics of Cashew Nut Shell Oil and Castor Oil Blends Using ZDDP as Additives | B46: Ravikiran, B. Sachin, T. Raghavendra & Gurukiran Kashyaup,R. Madhusudhana,S. L. Aravind | C46: MECH | D46: South | E46: Ravikiran | G46: Published | H46: 45476 | J46: 45669 | K46: =IF(AND(H46<>"",J46<>""),J46-H46,"") -> 193 | L46: Conference Paper | O46: Q4
A47: Enhancing biodegradable lubricants with SiO₂ and TiO₂ nanoparticles: effects on viscosity, tribological behavior, rheological performance, and sustainability | B47: Ravikiran, K R Prakash, K M Vaibhav, B sachin, C Durga Prasad, Ramesh N Babu | C47: MECH | D47: South | E47: Ravikiran | G47: Published | H47: 45660 | J47: 45748 | K47: =IF(AND(H47<>"",J47<>""),J47-H47,"") -> 88 | L47: Journal Article | O47: Q2 | P47: Yes
A48: Design and fabrication strategies for enhancing patient comfort and sustainability through PETG based 3D-printed orthoses | B48: B. Sachin, Charitha M. Rao, N. Keerthi Kumar,C. Durga Prasad,Ashish Kumar,Ravikiran,H. N. Manjunath, S. L. Aravind, Saravana Bavan | C48: MECH | D48: South | E48: B.Sachin | G48: Published | H48: 45471 | J48: 45665 | K48: =IF(AND(H48<>"",J48<>""),J48-H48,"") -> 194 | L48: Journal Article | O48: Q1
A49: Experimental Investigation on Mechanical Characteristics of Basalt-Aluminium Coated Glass Epoxy Composites with SiC Micro-Filler | B49: Ravikiran , Ajay Anand , Sri Charan T V , Vedaprasad , Pradeep Kumar V G and Venugopal H S | C49: MECH | D49: South | E49: Ravikiran | G49: Submitted | H49: 45730 | J49: 45869 | K49: =IF(AND(H49<>"",J49<>""),J49-H49,"") -> 139 | L49: Conference Paper | O49: Q4
A50: IoT Based Predictive Maintenance of Spur Gearbox | B50: Ravikiran, Yogesha K K , Akhil V M, Rakesh D, Rahul N Murthy, Dore Prasad | C50: MECH | D50: South | E50: Ravikiran | G50: Submitted | H50: 45660 | J50: 45899 | K50: =IF(AND(H50<>"",J50<>""),J50-H50,"") -> 239 | L50: Conference Paper | O50: Q4
A51: Study of the Hole Behavior Properties of ITO/Mo/Vopc/Mo/Al Devices by Varying the Temperature and Thickness via Impedance Spectroscopy | B51: R. Madhusudhana, H. Guddappa, P. Roopadevi, P. Ramyad, S. Sachin, Ravikiran, and B. Sachin | C51: MECH | D51: South | E51: R. Madhusudhana | G51: Accepted | H51: 45593 | J51: 45677 | K51: =IF(AND(H51<>"",J51<>""),J51-H51,"") -> 84 | L51: Journal Article | O51: Q3 | P51: Yes
A52: INITIAL ESTIMATES OF BAZILEVIC TYPE FUNCTIONS DEFINED BY LIMACON-SHAPED DOMAIN | B52: Tejas N S, H Orhan, Raju D S, Magesh N | C52: MATHS | D52: South | E52: H Orhan | F52: Contract Faculty | G52: Published | H52: 45566 | J52: 45903 | K52: =IF(AND(H52<>"",J52<>""),J52-H52,"") -> 337 | L52: Journal Article | M52: Iranian Journal of Science | O52: Q3 | P52: Yes
A53: A subclass of Bi-Bazilevic type functions associated with Generalized Laguerre polynomials | B53: N Magesh, Raju D S, Tejas N S | C53: MATHS | D53: South | E53: Tejas N S | F53: Contract Faculty | G53: Accepted | H53: 45680 | J53: 46045 | K53: =IF(AND(H53<>"",J53<>""),J53-H53,"") -> 365 | L53: Journal Article | M53: Communications in Korean Mathematical Scoiety | O53: Q3 | P53: Yes
A54: ESTIMATES OF THE INITIAL TAYLOR-MACLAURIN COEFFICIENTS OF A GENERAL SUBCLASS OF BI-BAZILEVIC TYPE FUNCTIONS | B54: Tejas N S, H Orhan, Raju D S, Magesh N | C54: MATHS | D54: South | E54: H Orhan | F54: Contract Faculty | G54: Published | H54: 45474 | J54: 45680 | K54: =IF(AND(H54<>"",J54<>""),J54-H54,"") -> 206 | L54: Journal Article | M54: General Mathematics
A55: A Generalized Subclass of Bi-bazilevic Functions Involving Gegenbauer Polynomials | B55: Yamini, Magesh N, Tejas N S, Raju D S | C55: MATHS | D55: South | E55: Magesh N | F55: Contract Faculty | G55: Published | H55: 45536 | J55: 45930 | K55: =IF(AND(H55<>"",J55<>""),J55-H55,"") -> 394 | L55: Journal Article | M55: Journal of Applied Mathematics and Informatic | O55: Q3 | P55: Yes
A56: A Machine Learning based Frame work for Predicting Overall Equipment Effectiveness (OEE) with Environmental Factors in Additive Manufacturing | B56: Aruna Mokhamatam, K R Prakash, Sharmila B S, Divya HV | C56: MECH | D56: South | E56: Aruna Mokhamatam | G56: Accepted | H56: 45667 | J56: 45742 | K56: =IF(AND(H56<>"",J56<>""),J56-H56,"") -> 75 | L56: Journal Article | O56: Q4
A57: Design of Steel Foot Over Bridge – A Proposal | B57: Gagana P, Vasanth Keshav, Manoj H S | C57: CIVIL | D57: South | E57: Vasanth Keshav | F57: Assistant Professor | G57: Accepted | H57: 45392 | J57: 45683 | K57: =IF(AND(H57<>"",J57<>""),J57-H57,"") -> 291 | L57: Book Chapter | M57: International Conference on Sustainable Infrastructure: Innovation, Opportunities and Challenges (SIIOC 2024) | O57: Q3 | AA57: PG Only
A58: Wind and Seismic Response Analysis of Cable Stayed Bridge– A Case Study | B58: Gagana P, Vasanth Keshav, Manoj H S | C58: CIVIL | D58: South | E58: Vasanth Keshav | F58: Assistant Professor | G58: Accepted | H58: 45392 | J58: 45683 | K58: =IF(AND(H58<>"",J58<>""),J58-H58,"") -> 291 | L58: Book Chapter | M58: International Conference on Sustainable Infrastructure: Innovation, Opportunities and Challenges (SIIOC 2024) | O58: Q3 | AA58: PG Only
A59: Effect of imperfection in non-linear static buckling of laminated composite hexagonal plate with incorporation of jute fibers | B59: Sathwik C R, Vasanth Keshav, Gouthamraj M R | C59: CIVIL | D59: South | E59: Vasanth Keshav | F59: Assistant Professor | G59: Accepted | H59: 45392 | J59: 45683 | K59: =IF(AND(H59<>"",J59<>""),J59-H59,"") -> 291 | L59: Book Chapter | M59: International Conference on Sustainable Infrastructure: Innovation, Opportunities and Challenges (SIIOC 2024) | O59: Q3 | AA59: PG Only
A60: Effect of boundary conditions on Non-linear static buckling of laminated composite pentagonal plate made of aloe vera fibers | B60: Gouthamraj M R, Vasanth Keshav, Sathwik C R | C60: CIVIL | D60: South | E60: Vasanth Keshav | F60: Assistant Professor | G60: Accepted | H60: 45392 | J60: 45683 | K60: =IF(AND(H60<>"",J60<>""),J60-H60,"") -> 291 | L60: Book Chapter | M60: International Conference on Sustainable Infrastructure: Innovation, Opportunities and Challenges (SIIOC 2024) | O60: Q3 | AA60: PG Only
A61: Effect of Radius of Curvature on Doubly Curved Cylindrical Shell made of Coir Fibers when subjected to in-plane loads | B61: Sathwik C R, Vasanth Keshav and GouthamRaj M R | C61: CIVIL | D61: South | E61: Vasanth Keshav | F61: Assistant Professor | G61: Published | H61: 45535 | J61: 46356 | K61: =IF(AND(H61<>"",J61<>""),J61-H61,"") -> 821 | L61: Book Chapter | M61: International Conference on Sustainable Infrastructure: Innovation, Opportunities and Challenges (SIIOC 2024) | O61: Q3 | AA61: PG Only
A62: Effect of radius of curvature on the singly curved cylindrical shell made of coir fibers when subjected to in-plane loads | B62: Gouthamraj M R, Vasanth Keshav, Sathwik C R | C62: CIVIL | D62: South | E62: Vasanth Keshav | F62: Assistant Professor | G62: Under Review | H62: 45535 | J62: 45748 | K62: =IF(AND(H62<>"",J62<>""),J62-H62,"") -> 213 | L62: Journal Article | P62: Yes | AA62: PG Only
A63: Investigation on concrete filled square hollow sections subjected to static and dynamic loads | B63: Sagar S, Vasanth Keshav | C63: CIVIL | D63: South | E63: Vasanth Keshav | F63: Assistant Professor | G63: Under Review | H63: 45535 | J63: 45748 | K63: =IF(AND(H63<>"",J63<>""),J63-H63,"") -> 213 | L63: Journal Article | P63: Yes | AA63: PG Only
A64: Effect of foundation type on the Seismic behaviour of Nuclear Reactor Building | B64: Gagana P, Manoj H S and Vasanth Keshav | C64: CIVIL | D64: South | E64: Gagana P | F64: Assistant Professor | G64: Under Review | H64: 45725 | J64: 45748 | K64: =IF(AND(H64<>"",J64<>""),J64-H64,"") -> 23 | L64: Journal Article | P64: Yes | AA64: PG Only
A65: Mechanical Properties of Laminated Composite Panel With Natural Fibers | B65: Niveditha K., Sushmitha K., Pooja R.M., Rakshitha C. and Vasanth Keshav | C65: CIVIL | D65: South | E65: Vasanth Keshav | F65: Assistant Professor | G65: Accepted | H65: 45698 | J65: 45734 | K65: =IF(AND(H65<>"",J65<>""),J65-H65,"") -> 36 | L65: Book Chapter | O65: Q3 | AA65: PG Only
A66: Enhancing Solar Radiation Forecasting using Machine Learning Algorithms | B66: Mahesh Kumar K M,Uppuluri Lakshmi Soundharya,Hemalatha R ,Anjanappa C,SUGANYA M J | C66: ECE | D66: South | E66: Anjanappa .C | G66: Accepted | H66: 45355 | J66: 45715 | K66: =IF(AND(H66<>"",J66<>""),J66-H66,"") -> 360 | L66: Journal Article | O66: Unspecified
A67: Investigation of slurry erosion wear behaviors on coir filled polypropylene composites | B67: Santosh Kumar *, H. N. Divakar , C. M. Veerabhadraswamy, Nandini T S Ravikumar Beeranur ,H. S. Kumar ,Manjunath Yadav , Anil Kumar S Kallimani | C67: MECH | D67: South | E67: Santosh Kumar | F67: Assistant Professor | G67: Accepted | H67: 45661 | J67: 45744 | K67: =IF(AND(H67<>"",J67<>""),J67-H67,"") -> 83 | L67: Journal Article | O67: Unspecified
A68: Revolutionizing Automobile Waste into Renewable Energy by Triboelectric Nanogenerators for Vehicle Safety | B68: Rumana Farheen Sagade Muktar Ahmed, Adarsh Raj Lingaraj, Divakar Holenarasipura Neelakantaiah, Sangamesha Madanahalli Ankanathappa, Krishnaveni Sannathammegowda | C68: MECH | D68: South | E68: Divakar Holenarasipura Neelakantaiah | G68: Published | H68: 45637 | J68: 45694 | K68: =IF(AND(H68<>"",J68<>""),J68-H68,"") -> 57 | L68: Journal Article | O68: Unspecified
A69: "The Effect of Ceramic Additives on the Mechanical Behavior of Carbon/Epoxy Composites" | B69: Sandeep.B Dr.H. N. Divakar Dr. Keerthiprasad K. S | C69: MECH | D69: South | E69: Sandeep.B (Manuscript id: 49021) | G69: Accepted | H69: 45732 | J69: 45751 | K69: =IF(AND(H69<>"",J69<>""),J69-H69,"") -> 19 | L69: Journal Article | O69: Unspecified
A70: Tribological Behaviour of Jute/Vinyl Ester Composites Impregnated with Alumina Filler. | B70: Prashanth, N.; Swamy, L. Ranganatha; Hemaraju; Kumar Santosh | C70: MECH | D70: South | E70: Santosh Kumar | G70: Accepted | H70: 45571 | J70: 45716 | K70: =IF(AND(H70<>"",J70<>""),J70-H70,"") -> 145 | L70: Journal Article | O70: Unspecified
A71: Effect of Ceramic Boron Carbide Particles Addition on the Mechanical and Microstructural Characteristics of Al7020 Alloy Composites | B71: Shrishail Basappa Angadi , Santosh Kumar , Madeva Nagaral , Virupaxi Auardi , Balaraj Valukula | C71: MECH | D71: South | E71: Madeva Nagaral | F71: Assistant Professor | G71: Accepted | H71: 45427 | J71: 45659 | K71: =IF(AND(H71<>"",J71<>""),J71-H71,"") -> 232 | L71: Journal Article | O71: Unspecified
A72: Enhancing Building Demolition Safety Code of Practice: Reconstructing the codal Provision of Demolition of Buildings | B72: Soumya B Gouda and Balaji N C | C72: CIVIL | D72: South | E72: Balaji N C | F72: Associate Professor | G72: Accepted | H72: 45392 | J72: 45683 | K72: =IF(AND(H72<>"",J72<>""),J72-H72,"") -> 291 | L72: Book Chapter | M72: International Conference on Sustainable Infrastructure: Innovation, Opportunities and Challenges (SIIOC 2024) | O72: Q3
A73: Methodology for Shear and Flexural Strengthening of RC Beams with NSM Technique | B73: Fiza Naaz, Soumya B Gouda and Balaji N C | C73: CIVIL | D73: South | E73: Balaji N C | F73: Associate Professor | G73: Accepted | H73: 45392 | J73: 45683 | K73: =IF(AND(H73<>"",J73<>""),J73-H73,"") -> 291 | L73: Book Chapter | M73: International Conference on Sustainable Infrastructure: Innovation, Opportunities and Challenges (SIIOC 2024) | O73: Q3
A74: Ensuring safety in construction of concrete frames: Reviewing the codal provisions for erection | B74: Fiza Naaz and Balaji N C | C74: CIVIL | D74: South | E74: Balaji N C | F74: Associate Professor | G74: Accepted | H74: 45392 | J74: 45683 | K74: =IF(AND(H74<>"",J74<>""),J74-H74,"") -> 291 | L74: Book Chapter | M74: International Conference on Sustainable Infrastructure: Innovation, Opportunities and Challenges (SIIOC 2024) | O74: Q3 | AA74: PG Only | AB74: No
A75: Evaluating the structural behaviour and suitability of the surface repair material used for repairing concrete structural elements | B75: Kaveramma A. V. , Chandan K. R. , Dhananjay Murthy K. , Monglong Phom, Balaji N. C., and Gourav K. | C75: CIVIL | D75: South | E75: Balaji N C | F75: Associate Professor | G75: Accepted | H75: 45392 | J75: 45683 | K75: =IF(AND(H75<>"",J75<>""),J75-H75,"") -> 291 | L75: Book Chapter | M75: International Conference on Sustainable Infrastructure: Innovation, Opportunities and Challenges (SIIOC 2024) | O75: Q3 | AA75: PG Only | AB75: No
A76: Assessing the quality of drinking water filtered through commercial filters and also designing suitable gravity water filters for residential usage | B76: Balaji. N. C. Kiran Kumar. S., Hemanth Urs. R., Mahendra. N. and Dhanush. L | C76: CIVIL | D76: South | E76: Balaji N C | F76: Associate Professor | G76: Published | H76: 45392 | J76: 45683 | K76: =IF(AND(H76<>"",J76<>""),J76-H76,"") -> 291 | L76: Book Chapter | M76: International Conference on Sustainable Infrastructure: Innovation, Opportunities and Challenges (SIIOC 2024) | O76: Q3 | AA76: PG Only | AB76: No
A77: Experimental study on behavior of steel fiber reinforced concrete beams subjected to combined flexure, shear and torsion | B77: T H Sadashiva Murthy and N C Balaji, Manohar Y M, Mohammed Sakhib | C77: CIVIL | D77: South | E77: Balaji N C | F77: Associate Professor | G77: Accepted | H77: 45698 | J77: 45734 | K77: =IF(AND(H77<>"",J77<>""),J77-H77,"") -> 36 | L77: Book Chapter | M77: International Conference on Sustainable Technologies (ICST) – 2025 | O77: Q3 | AA77: Mixed | AB77: No
A78: Experimental Study on Behaviour of Steel Fibre Reinforced Concrete Beam with Partial Replacement of Cement by Flyash Subjected to Combined Flexure, Shear and Torsion | B78: T H Sadashiva Murthy and N C Balaji, Mohammed Sakhib, Manohar Y M | C78: CIVIL | D78: South | E78: Balaji N C | F78: Associate Professor | G78: Accepted | H78: 45698 | J78: 45734 | K78: =IF(AND(H78<>"",J78<>""),J78-H78,"") -> 36 | L78: Book Chapter | M78: International Conference on Sustainable Technologies (ICST) – 2025 | O78: Q3 | AA78: Mixed | AB78: No
A79: SYNTHESIS OF ALKALI ACTIVATED ARTIFICIAL AGGREGATE AND THEIR IMPACT STUDIES ON PERFORMANCE OF CONCRETE | B79: Basavana Gowda S N, Thanu H P, Sharan Kumar Goudar, Punith B Kotagi, Vinod N T | C79: CIVIL | D79: South | E79: Punith B Kotagi | F79: Associate Professor | G79: Under Review | H79: 45731 | J79: 45899 | K79: =IF(AND(H79<>"",J79<>""),J79-H79,"") -> 168 | L79: Conference Paper | O79: Q3
A80: Advanced Predictive Approaches for Accident Forecasting to Enhance Road Safety | B80: Prasad Manoj, Punith B Kotagi, Kerekoppa Chandrashekar Manjunath | C80: CIVIL | D80: South | E80: Punith B Kotagi | F80: Associate Professor | G80: Accepted | H80: 45685 | J80: 45868 | K80: =IF(AND(H80<>"",J80<>""),J80-H80,"") -> 183 | L80: Journal Article | O80: Q3
A81: Robust Direction of Arrival Estimation using improved Coprime Array for Wireless Communication Applications | B81: Shashidhara K. S., K. N. Venu, I. G. Saritha, Raghu Jayaramu, Veerendra Dakulagi | C81: ECE | D81: South | E81: Shashidhara K. S | G81: Published | H81: 45554 | J81: 45666 | K81: =IF(AND(H81<>"",J81<>""),J81-H81,"") -> 112 | L81: Journal Article | O81: Q2
A82: Comprehensive Track Unswapping for Improved Tracker Performance | B82: J. Raghu, T. L. Purushottama, B Pardhasaradhi, P. Srihari, R. Tharmarasa and T. Kirubarajan, | C82: ECE | D82: South | E82: Raghu J | G82: Published | H82: 45485 | J82: 45732 | K82: =IF(AND(H82<>"",J82<>""),J82-H82,"") -> 247 | L82: Journal Article | O82: Q1 | P82: Yes
A83: Expeimental Investigations on the Mechanical Behaviour of basaltfabric reinforced epoxycomposites | B83: Kiran R, Prakash.K.R,Suresha Bheemappa | C83: MECH | D83: South | E83: Kiran.R | G83: Published | H83: 45664 | J83: 45716 | K83: =IF(AND(H83<>"",J83<>""),J83-H83,"") -> 52 | L83: Journal Article | O83: Unspecified
A84: Interpretable machine learning model for temperature prediction in coal pulverizes of thermal power plants in International Journal of Coal Preparation and Utilization | B84: Pullanikkattil, Suhailam, Yerolla Raju and Besta, Chandra Shekar | C84: EEE | D84: South | E84: Chadra Shekar Besta | G84: Published | H84: 45638 | J84: 45709 | K84: =IF(AND(H84<>"",J84<>""),J84-H84,"") -> 71 | L84: Journal Article | O84: Q2 | P84: Yes
A85: Enhancing Stability in Cascade Processes through Particle Swarm Optimization and Internal Model Controller | B85: Yerolla Raju, Pullanikkattil Suhailam, Besta Chandra Shekar | C85: EEE | D85: South | E85: Raju Yerolla | G85: Accepted | H85: 45705 | J85: 45889 | K85: =IF(AND(H85<>"",J85<>""),J85-H85,"") -> 184 | L85: Journal Article | O85: Q3
A86: An Experimental Data-Driven Mathematical Model and Machine Learning Approach For Damage Detection in Spur Gears | B86: Imran M Jamadar, Nihan Pasha K M, Prasanta Kumar Samal, Nithin M | C86: MECH | D86: South | E86: Imran M Jamadar | F86: Professor | G86: Submitted | H86: 45738 | J86: 45931 | K86: =IF(AND(H86<>"",J86<>""),J86-H86,"") -> 193 | L86: Journal Article | O86: Q3
A87: Machine learning Analysis of Poorly conducting homogeneous fluid in electro maganetic field | B87: Shubha Nagaraj | C87: MATHS | D87: South | E87: Harsha S | G87: Submitted | H87: 45748 | J87: 45899 | K87: =IF(AND(H87<>"",J87<>""),J87-H87,"") -> 151 | L87: Journal Article | O87: Q2
A88: Multi Robot Approaches for Sustainable Inspection and Maintenance :Afocus on Occupancy Map Merging | B88: Arpitha Shankar, Prakash K.R. | C88: MECH | D88: South | E88: Arpitha Shankar | G88: Submitted | H88: 45740 | J88: 45869 | K88: =IF(AND(H88<>"",J88<>""),J88-H88,"") -> 129 | L88: Conference Paper | O88: Unspecified
A89: Experiential Learning in Engineering Education for Bridging the gap between Academia and Industry | B89: Remya Jayachandran, Salila Hedge | C89: ECE | D89: South | E89: Remya Jayachandran | F89: Assistant Professor | G89: Accepted | H89: 45682 | J89: 46112 | K89: =IF(AND(H89<>"",J89<>""),J89-H89,"") -> 430 | L89: Journal Article | M89: JEET - Journal of Engineering Education and Transformation | O89: Q2 | P89: No
A90: CMOS-Based Memristor Emulator Circuit for Audio Signal Processing in Hearing Aid Applications | B90: Remya Jayachandran, Sudeep kumar, Sanjay H, Varshini H R, Prekshadeep S P, Sangeetha A Shayana | C90: ECE | D90: South | E90: Remya Jayachandran | F90: Assistant Professor | G90: Published | H90: 45688 | J90: 45726 | K90: =IF(AND(H90<>"",J90<>""),J90-H90,"") -> 38 | L90: Conference Paper | M90: IEEE EDKCON 2025 | O90: Unspecified | Q90: https://doi.org/10.1109/DevIC63749.2025.11012243
A91: SQ-3DP: A Novel Dataset for machine learning Optimization in Additive Manufacturing | B91: Aruna Mokhamatam, K R Prakash, Sharmila B S | C91: MECH | D91: South | E91: Aruna Mokhamatam | G91: Under Review | H91: 45712 | J91: 45930 | K91: =IF(AND(H91<>"",J91<>""),J91-H91,"") -> 218 | L91: Journal Article | O91: Unspecified
A92: SUSTAINABLE AUTOMATED PLASTIC WASTE SEGREGATION SYSTEM USING IOT AND IMAGE PROCESSING FOR MATERIAL RECOVERY CENTERS | B92: Remya Jayachandran, Nidhishree, Anush R Halappanavar, Laxman K Budni, Abhishesk C M, Charan S Hegde, and Rupesh S | C92: ECE | D92: South | E92: Remya Jayachandran | F92: Assistant Professor | G92: Accepted | H92: 45672 | J92: 45689 | K92: =IF(AND(H92<>"",J92<>""),J92-H92,"") -> 17 | L92: Conference Paper | M92: ICST 2025 | O92: Unspecified
A93: Transforming Healthcare through Smart Health Systems: Harnessing Technology for Enhanced Patient Care | B93: Remya Jayachandran, Bhargava Dantapur, Aneeta S Antony, Rohini Nagapadma | C93: ECE | D93: South | E93: Remya Jayachandran | F93: Assistant Professor | G93: Published | H93: 45168 | J93: 45680 | K93: =IF(AND(H93<>"",J93<>""),J93-H93,"") -> 512 | L93: Book Chapter | M93: Transforming Healthcare Sector Through Artificial Intelligence and Environmental Sustainability | O93: Q2 | Q93: https://scholar.google.com/scholar?oi=bibs&cluster=4618592191113981194&btnI=1&hl=en
A94: DESIGN OF ADVANCED MOSFET ARCHITECTURES | B94: Remya Jayachandran, Salila Hegde | C94: ECE | D94: South | E94: Remya Jayachandran | F94: Assistant Professor | G94: Published | H94: 45505 | J94: 45667 | K94: =IF(AND(H94<>"",J94<>""),J94-H94,"") -> 162 | L94: Book Chapter | M94: Micro and Nano Semiconductor Devices for Digital, Analog and Sensor Design | O94: Q2 | Q94: https://doi.org/10.1002/9781394307340.ch1
A95: EXPLORING THE SYNERGY OF ARTIFICIAL INTELLIGENCE AND INTERNET OF THINGS (AIOT) IN SMART HEALTHCARE AND SMART CITIES FOR ENHANCED CONNECTIVITY AND EFFICIENCY | B95: Remya Jayachandran, Annangi Saikiran Babu, Aniruddh Adiga, Rupesh S, Edet Bijoy Kumaradhas | C95: ECE | D95: South | E95: Remya Jayachandran | F95: Assistant Professor | G95: Accepted | H95: 45366 | J95: 45636 | K95: =IF(AND(H95<>"",J95<>""),J95-H95,"") -> 270 | L95: Book Chapter | O95: Q2
A96: Fundamentals of Hydrogen Energy | B96: Rupesh S, Deepanraj Balakrishnan, Aravind L, Remya Jayachandran | C96: ECE | D96: South | E96: Remya Jayachandran | F96: Assistant Professor | G96: Published | H96: 45422 | J96: 45662 | K96: =IF(AND(H96<>"",J96<>""),J96-H96,"") -> 240 | L96: Book Chapter | M96: Fuelling the Future | O96: Q1 | Q96: https://doi.org/10.1016/B978-0-443-34090-1.00007-5
A97: Spiking neuron cell using FinFET based OTA memristor emulator for Area Efficient Non-uniform Filter Bank in Hearing Aid Applications | B97: Remya Jayachandran, Shaeen K, Veena M K | C97: ECE | D97: South | E97: Remya Jayachandran | F97: Assistant Professor | G97: Under Review | H97: 45641 | J97: 46173 | K97: =IF(AND(H97<>"",J97<>""),J97-H97,"") -> 532 | L97: Journal Article | P97: Yes
A98: FPGA-Based I2C Master Controller for Real-Time Temperature Monitoring in Neonatal Radiant Warmers | B98: Vinay G, Sahana, Remya Jayachandran | C98: ECE | D98: South | E98: Remya Jayachandran | F98: Assistant Professor | G98: Under Review | H98: 45747 | J98: 46173 | K98: =IF(AND(H98<>"",J98<>""),J98-H98,"") -> 426 | L98: Conference Paper | O98: Q1
A99: Steel fibre reinforced concrete (SFRC) under repeated slow cyclic loading in tension - Experimental and Theoretical Studies | B99: Jayanth K, Suresh G S | C99: CIVIL | D99: South | E99: Jayanth K | G99: Published | H99: 45657 | J99: 45752 | K99: =IF(AND(H99<>"",J99<>""),J99-H99,"") -> 95 | L99: Journal Article | O99: Q2 | P99: Yes
A100: Steel fibre reinforced concrete (SFRC) under repeated slow cyclic loading in flexure - Experimental and Finite element Studies | B100: Jayanth K, Suresh G S | C100: CIVIL | D100: South | E100: Jayanth K | G100: Under Review | H100: 45657 | J100: 45838 | K100: =IF(AND(H100<>"",J100<>""),J100-H100,"") -> 181 | L100: Journal Article | O100: Q2 | P100: Yes
...

Sheet Read Me
B2: NIE Publication Status Tracker — User Guide
B4: PURPOSE | C4: Track all NIE faculty research publications. Supports pipeline monitoring and NIRF ranking strategy.
B5: BLUE COLUMNS | C5: Existing fields, cleaned and standardised from the original tracker.
B6: RED COLUMNS | C6: HIGH PRIORITY new fields for NIRF quality score: Journal Name, Impact Factor, DOI, Citation Count.
B7: GREEN COLUMNS | C7: New planning, collaboration, and funding fields. Fill progressively as information is available.
B8: DEPARTMENT | C8: Use standard codes only: CSE, ISE, ECE, MECH, CIVIL, EEE, MCA, MATHS, PHY, CHEM. Dropdown enforced.
B9: SCOPUS QUARTILE | C9: Now a separate column. Select Q1/Q2/Q3/Q4/Unspecified/Not Scopus from dropdown.
B10: WEB OF SCIENCE | C10: Select Yes or No. SCI, SCIE, and ESCI all qualify as Yes.
B11: IMPACT FACTOR | C11: Enter the journal IF at time of submission. Use 3 decimal places (e.g., 4.521).
B12: CITATION COUNT | C12: Update annually before NIRF submission. Log the date in Citation Updated On column.
B13: ELAPSED DAYS | C13: Auto-calculated from Start Date to Acceptance Date. Do not edit manually. | G13: V
B14: ANALYTICS TAB | C14: Auto-updating summaries by status, Scopus quartile, and department. Do not edit directly.
B15: DATA ENTRY TIP | C15: Use the dropdown menus wherever available to maintain consistency for Analytics.

Sheet Analytics
B2: NIE RESEARCH PUBLICATION DASHBOARD | W2: Dept | X2: Fac#
W3: CSE | X3: 39
B4: TOTAL PUBLISHED | H4: IN PIPELINE | L4: PUBLICATIONS / FACULTY | R4: Q1 + Q2 PAPERS | W4: ISE | X4: 29
B5: =COUNTIF('Publication Status Tracker NIE'!G:G,"Published") -> 216 | H5: =COUNTIF('Publication Status Tracker NIE'!G:G,"Accepted")+COUNTIF('Publication Status Tracker NIE'!G:G,"Under Review")+COUNTIF('Publication Status Tracker NIE'!G:G,"Submitted")+COUNTIF('Publication Status Tracker NIE'!G:G,"Revision Required") -> 260 | L5: =IFERROR(COUNTIF('Publication Status Tracker NIE'!G:G,"Published")/'Dept & Faculty'!G11,0) -> 27 | R5: =COUNTIF('Publication Status Tracker NIE'!O:O,"Q1")+COUNTIF('Publication Status Tracker NIE'!O:O,"Q2") -> 170 | W5: ECE | X5: 23
B6: papers across NIE | H6: accepted + under review + submitted | L6: vs target of 3.00 per year | R6: high-quality indexed papers | W6: MECH | X6: 31
W7: CIVIL | X7: 22
W8: EEE | X8: 15
B9: ▶ PUBLICATION PIPELINE | H9: ▶ QUALITY MIX | M9: ▶ PUBLICATION TYPE | R9: ▶ CAMPUS SPLIT | W9: MCA | X9: 12
B10: Draft / WIP | C10: =COUNTIF('Publication Status Tracker NIE'!G:G,"Draft / Work in Progress") -> 35 | D10: =IFERROR(C10/SUM(C10:C16)*100,0) -> 6.7567568 | H10: Q1 (Scopus) | I10: =COUNTIF('Publication Status Tracker NIE'!O:O,"Q1") -> 65 | J10: =IFERROR(I10/SUM(I10:I15)*100,0) -> 11.861314 | M10: Journal Article | N10: =COUNTIF('Publication Status Tracker NIE'!L:L,"Journal Article") -> 313 | O10: =IFERROR(N10/SUM(N10:N14)*100,0) -> 63.877551 | R10: South Campus | S10: =COUNTIF('Publication Status Tracker NIE'!D:D,"South") -> 321 | T10: =IFERROR(S10/SUM(S10:S11)*100,0) -> 61.494253 | W10: MATHS | X10: 12
B11: Submitted | C11: =COUNTIF('Publication Status Tracker NIE'!G:G,"Submitted") -> 41 | D11: =IFERROR(C11/SUM(C10:C16)*100,0) -> 7.9150579 | H11: Q2 (Scopus) | I11: =COUNTIF('Publication Status Tracker NIE'!O:O,"Q2") -> 105 | J11: =IFERROR(I11/SUM(I10:I15)*100,0) -> 19.160584 | M11: Conference Paper | N11: =COUNTIF('Publication Status Tracker NIE'!L:L,"Conference Paper") -> 110 | O11: =IFERROR(N11/SUM(N10:N14)*100,0) -> 22.44898 | R11: North Campus | S11: =COUNTIF('Publication Status Tracker NIE'!D:D,"North") -> 201 | T11: =IFERROR(S11/SUM(S10:S11)*100,0) -> 38.505747 | W11: PHY | X11: 9
B12: Under Review | C12: =COUNTIF('Publication Status Tracker NIE'!G:G,"Under Review") -> 83 | D12: =IFERROR(C12/SUM(C10:C16)*100,0) -> 16.023166 | H12: Q3 (Scopus) | I12: =COUNTIF('Publication Status Tracker NIE'!O:O,"Q3") -> 96 | J12: =IFERROR(I12/SUM(I10:I15)*100,0) -> 17.518248 | M12: Book Chapter | N12: =COUNTIF('Publication Status Tracker NIE'!L:L,"Book Chapter") -> 60 | O12: =IFERROR(N12/SUM(N10:N14)*100,0) -> 12.244898 | W12: CHEM | X12: 5
B13: Revision Reqd | C13: =COUNTIF('Publication Status Tracker NIE'!G:G,"Revision Required") -> 16 | D13: =IFERROR(C13/SUM(C10:C16)*100,0) -> 3.0888031 | H13: Q4 (Scopus) | I13: =COUNTIF('Publication Status Tracker NIE'!O:O,"Q4") -> 49 | J13: =IFERROR(I13/SUM(I10:I15)*100,0) -> 8.9416058 | M13: Review Article | N13: =COUNTIF('Publication Status Tracker NIE'!L:L,"Review Article") -> 4 | O13: =IFERROR(N13/SUM(N10:N14)*100,0) -> 0.81632653
B14: Accepted | C14: =COUNTIF('Publication Status Tracker NIE'!G:G,"Accepted") -> 120 | D14: =IFERROR(C14/SUM(C10:C16)*100,0) -> 23.166023 | H14: WoS (SCI/SCIE) | I14: =COUNTIF('Publication Status Tracker NIE'!P:P,"Yes") -> 146 | J14: =IFERROR(I14/SUM(I10:I15)*100,0) -> 26.642336 | M14: Other | N14: =COUNTIF('Publication Status Tracker NIE'!L:L,"Other Publication") -> 3 | O14: =IFERROR(N14/SUM(N10:N14)*100,0) -> 0.6122449
B15: Published | C15: =COUNTIF('Publication Status Tracker NIE'!G:G,"Published") -> 216 | D15: =IFERROR(C15/SUM(C10:C16)*100,0) -> 41.698842 | H15: Unspecified | I15: =COUNTIF('Publication Status Tracker NIE'!O:O,"Unspecified") -> 87 | J15: =IFERROR(I15/SUM(I10:I15)*100,0) -> 15.875912
B16: Rejected | C16: =COUNTIF('Publication Status Tracker NIE'!G:G,"Rejected") -> 7 | D16: =IFERROR(C16/SUM(C10:C16)*100,0) -> 1.3513514
B17: TOTAL | C17: =SUM(C10:C16) -> 518 | D17: 100%
B19: ▶ DEPARTMENT TARGET SCORECARD (Target: D4 publications per faculty per year)
C20: Department | D20: Faculty | E20: Target | F20: Published | G20: Pipeline | H20: Rate | I20: Gap | J20: Q1+Q2 | K20: Q1+Q2% | L20: Draft/WIP | M20: Progress % | N20: Status
C21: CSE | D21: 39 | E21: =D21*$D$4 -> 0 | F21: =COUNTIFS('Publication Status Tracker NIE'!C:C,C21,'Publication Status Tracker NIE'!G:G,"Published") -> 26 | G21: =COUNTIFS('Publication Status Tracker NIE'!C:C,C21,'Publication Status Tracker NIE'!G:G,"Accepted")+COUNTIFS('Publication Status Tracker NIE'!C:C,C21,'Publication Status Tracker NIE'!G:G,"Under Review")+COUNTIFS('Publication Status Tracker NIE'!C:C,C21,'Publication Status Tracker NIE'!G:G,"Submitted")+COUNTIFS('Publication Status Tracker NIE'!C:C,C21,'Publication Status Tracker NIE'!G:G,"Revision Required") -> 37 | H21: =IFERROR(F21/D21,0) -> 0.66666667 | I21: =E21-F21 -> -26 | J21: =COUNTIFS('Publication Status Tracker NIE'!C:C,C21,'Publication Status Tracker NIE'!O:O,"Q1")+COUNTIFS('Publication Status Tracker NIE'!C:C,C21,'Publication Status Tracker NIE'!O:O,"Q2") -> 13 | K21: =IFERROR(J21/F21*100,0) -> 50 | L21: =COUNTIFS('Publication Status Tracker NIE'!C:C,C21,'Publication Status Tracker NIE'!G:G,"Draft / Work in Progress") -> 6 | M21: =IFERROR(F21/E21*100,0) -> 0 | N21: =IF(H21>=$D$4,"✓ On Target",IF(H21>=$D$4*0.66,"⚠ Approaching",IF(H21>=$D$4*0.33,"↑ Improving","✗ Needs Action"))) -> ✓ On Target
C22: ISE | D22: 29 | E22: =D22*$D$4 -> 0 | F22: =COUNTIFS('Publication Status Tracker NIE'!C:C,C22,'Publication Status Tracker NIE'!G:G,"Published") -> 30 | G22: =COUNTIFS('Publication Status Tracker NIE'!C:C,C22,'Publication Status Tracker NIE'!G:G,"Accepted")+COUNTIFS('Publication Status Tracker NIE'!C:C,C22,'Publication Status Tracker NIE'!G:G,"Under Review")+COUNTIFS('Publication Status Tracker NIE'!C:C,C22,'Publication Status Tracker NIE'!G:G,"Submitted")+COUNTIFS('Publication Status Tracker NIE'!C:C,C22,'Publication Status Tracker NIE'!G:G,"Revision Required") -> 41 | H22: =IFERROR(F22/D22,0) -> 1.0344828 | I22: =E22-F22 -> -30 | J22: =COUNTIFS('Publication Status Tracker NIE'!C:C,C22,'Publication Status Tracker NIE'!O:O,"Q1")+COUNTIFS('Publication Status Tracker NIE'!C:C,C22,'Publication Status Tracker NIE'!O:O,"Q2") -> 16 | K22: =IFERROR(J22/F22*100,0) -> 53.333333 | L22: =COUNTIFS('Publication Status Tracker NIE'!C:C,C22,'Publication Status Tracker NIE'!G:G,"Draft / Work in Progress") -> 13 | M22: =IFERROR(F22/E22*100,0) -> 0 | N22: =IF(H22>=$D$4,"✓ On Target",IF(H22>=$D$4*0.66,"⚠ Approaching",IF(H22>=$D$4*0.33,"↑ Improving","✗ Needs Action"))) -> ✓ On Target
C23: ECE | D23: 23 | E23: =D23*$D$4 -> 0 | F23: =COUNTIFS('Publication Status Tracker NIE'!C:C,C23,'Publication Status Tracker NIE'!G:G,"Published") -> 29 | G23: =COUNTIFS('Publication Status Tracker NIE'!C:C,C23,'Publication Status Tracker NIE'!G:G,"Accepted")+COUNTIFS('Publication Status Tracker NIE'!C:C,C23,'Publication Status Tracker NIE'!G:G,"Under Review")+COUNTIFS('Publication Status Tracker NIE'!C:C,C23,'Publication Status Tracker NIE'!G:G,"Submitted")+COUNTIFS('Publication Status Tracker NIE'!C:C,C23,'Publication Status Tracker NIE'!G:G,"Revision Required") -> 49 | H23: =IFERROR(F23/D23,0) -> 1.2608696 | I23: =E23-F23 -> -29 | J23: =COUNTIFS('Publication Status Tracker NIE'!C:C,C23,'Publication Status Tracker NIE'!O:O,"Q1")+COUNTIFS('Publication Status Tracker NIE'!C:C,C23,'Publication Status Tracker NIE'!O:O,"Q2") -> 33 | K23: =IFERROR(J23/F23*100,0) -> 113.7931 | L23: =COUNTIFS('Publication Status Tracker NIE'!C:C,C23,'Publication Status Tracker NIE'!G:G,"Draft / Work in Progress") -> 9 | M23: =IFERROR(F23/E23*100,0) -> 0 | N23: =IF(H23>=$D$4,"✓ On Target",IF(H23>=$D$4*0.66,"⚠ Approaching",IF(H23>=$D$4*0.33,"↑ Improving","✗ Needs Action"))) -> ✓ On Target
C24: MECH | D24: 31 | E24: =D24*$D$4 -> 0 | F24: =COUNTIFS('Publication Status Tracker NIE'!C:C,C24,'Publication Status Tracker NIE'!G:G,"Published") -> 21 | G24: =COUNTIFS('Publication Status Tracker NIE'!C:C,C24,'Publication Status Tracker NIE'!G:G,"Accepted")+COUNTIFS('Publication Status Tracker NIE'!C:C,C24,'Publication Status Tracker NIE'!G:G,"Under Review")+COUNTIFS('Publication Status Tracker NIE'!C:C,C24,'Publication Status Tracker NIE'!G:G,"Submitted")+COUNTIFS('Publication Status Tracker NIE'!C:C,C24,'Publication Status Tracker NIE'!G:G,"Revision Required") -> 40 | H24: =IFERROR(F24/D24,0) -> 0.67741935 | I24: =E24-F24 -> -21 | J24: =COUNTIFS('Publication Status Tracker NIE'!C:C,C24,'Publication Status Tracker NIE'!O:O,"Q1")+COUNTIFS('Publication Status Tracker NIE'!C:C,C24,'Publication Status Tracker NIE'!O:O,"Q2") -> 17 | K24: =IFERROR(J24/F24*100,0) -> 80.952381 | L24: =COUNTIFS('Publication Status Tracker NIE'!C:C,C24,'Publication Status Tracker NIE'!G:G,"Draft / Work in Progress") -> 0 | M24: =IFERROR(F24/E24*100,0) -> 0 | N24: =IF(H24>=$D$4,"✓ On Target",IF(H24>=$D$4*0.66,"⚠ Approaching",IF(H24>=$D$4*0.33,"↑ Improving","✗ Needs Action"))) -> ✓ On Target
C25: CIVIL | D25: 22 | E25: =D25*$D$4 -> 0 | F25: =COUNTIFS('Publication Status Tracker NIE'!C:C,C25,'Publication Status Tracker NIE'!G:G,"Published") -> 12 | G25: =COUNTIFS('Publication Status Tracker NIE'!C:C,C25,'Publication Status Tracker NIE'!G:G,"Accepted")+COUNTIFS('Publication Status Tracker NIE'!C:C,C25,'Publication Status Tracker NIE'!G:G,"Under Review")+COUNTIFS('Publication Status Tracker NIE'!C:C,C25,'Publication Status Tracker NIE'!G:G,"Submitted")+COUNTIFS('Publication Status Tracker NIE'!C:C,C25,'Publication Status Tracker NIE'!G:G,"Revision Required") -> 33 | H25: =IFERROR(F25/D25,0) -> 0.54545455 | I25: =E25-F25 -> -12 | J25: =COUNTIFS('Publication Status Tracker NIE'!C:C,C25,'Publication Status Tracker NIE'!O:O,"Q1")+COUNTIFS('Publication Status Tracker NIE'!C:C,C25,'Publication Status Tracker NIE'!O:O,"Q2") -> 18 | K25: =IFERROR(J25/F25*100,0) -> 150 | L25: =COUNTIFS('Publication Status Tracker NIE'!C:C,C25,'Publication Status Tracker NIE'!G:G,"Draft / Work in Progress") -> 0 | M25: =IFERROR(F25/E25*100,0) -> 0 | N25: =IF(H25>=$D$4,"✓ On Target",IF(H25>=$D$4*0.66,"⚠ Approaching",IF(H25>=$D$4*0.33,"↑ Improving","✗ Needs Action"))) -> ✓ On Target
C26: EEE | D26: 15 | E26: =D26*$D$4 -> 0 | F26: =COUNTIFS('Publication Status Tracker NIE'!C:C,C26,'Publication Status Tracker NIE'!G:G,"Published") -> 9 | G26: =COUNTIFS('Publication Status Tracker NIE'!C:C,C26,'Publication Status Tracker NIE'!G:G,"Accepted")+COUNTIFS('Publication Status Tracker NIE'!C:C,C26,'Publication Status Tracker NIE'!G:G,"Under Review")+COUNTIFS('Publication Status Tracker NIE'!C:C,C26,'Publication Status Tracker NIE'!G:G,"Submitted")+COUNTIFS('Publication Status Tracker NIE'!C:C,C26,'Publication Status Tracker NIE'!G:G,"Revision Required") -> 15 | H26: =IFERROR(F26/D26,0) -> 0.6 | I26: =E26-F26 -> -9 | J26: =COUNTIFS('Publication Status Tracker NIE'!C:C,C26,'Publication Status Tracker NIE'!O:O,"Q1")+COUNTIFS('Publication Status Tracker NIE'!C:C,C26,'Publication Status Tracker NIE'!O:O,"Q2") -> 4 | K26: =IFERROR(J26/F26*100,0) -> 44.444444 | L26: =COUNTIFS('Publication Status Tracker NIE'!C:C,C26,'Publication Status Tracker NIE'!G:G,"Draft / Work in Progress") -> 3 | M26: =IFERROR(F26/E26*100,0) -> 0 | N26: =IF(H26>=$D$4,"✓ On Target",IF(H26>=$D$4*0.66,"⚠ Approaching",IF(H26>=$D$4*0.33,"↑ Improving","✗ Needs Action"))) -> ✓ On Target
C27: MCA | D27: 12 | E27: =D27*$D$4 -> 0 | F27: =COUNTIFS('Publication Status Tracker NIE'!C:C,C27,'Publication Status Tracker NIE'!G:G,"Published") -> 19 | G27: =COUNTIFS('Publication Status Tracker NIE'!C:C,C27,'Publication Status Tracker NIE'!G:G,"Accepted")+COUNTIFS('Publication Status Tracker NIE'!C:C,C27,'Publication Status Tracker NIE'!G:G,"Under Review")+COUNTIFS('Publication Status Tracker NIE'!C:C,C27,'Publication Status Tracker NIE'!G:G,"Submitted")+COUNTIFS('Publication Status Tracker NIE'!C:C,C27,'Publication Status Tracker NIE'!G:G,"Revision Required") -> 1 | H27: =IFERROR(F27/D27,0) -> 1.5833333 | I27: =E27-F27 -> -19 | J27: =COUNTIFS('Publication Status Tracker NIE'!C:C,C27,'Publication Status Tracker NIE'!O:O,"Q1")+COUNTIFS('Publication Status Tracker NIE'!C:C,C27,'Publication Status Tracker NIE'!O:O,"Q2") -> 0 | K27: =IFERROR(J27/F27*100,0) -> 0 | L27: =COUNTIFS('Publication Status Tracker NIE'!C:C,C27,'Publication Status Tracker NIE'!G:G,"Draft / Work in Progress") -> 2 | M27: =IFERROR(F27/E27*100,0) -> 0 | N27: =IF(H27>=$D$4,"✓ On Target",IF(H27>=$D$4*0.66,"⚠ Approaching",IF(H27>=$D$4*0.33,"↑ Improving","✗ Needs Action"))) -> ✓ On Target
C28: MATHS | D28: 12 | E28: =D28*$D$4 -> 0 | F28: =COUNTIFS('Publication Status Tracker NIE'!C:C,C28,'Publication Status Tracker NIE'!G:G,"Published") -> 9 | G28: =COUNTIFS('Publication Status Tracker NIE'!C:C,C28,'Publication Status Tracker NIE'!G:G,"Accepted")+COUNTIFS('Publication Status Tracker NIE'!C:C,C28,'Publication Status Tracker NIE'!G:G,"Under Review")+COUNTIFS('Publication Status Tracker NIE'!C:C,C28,'Publication Status Tracker NIE'!G:G,"Submitted")+COUNTIFS('Publication Status Tracker NIE'!C:C,C28,'Publication Status Tracker NIE'!G:G,"Revision Required") -> 17 | H28: =IFERROR(F28/D28,0) -> 0.75 | I28: =E28-F28 -> -9 | J28: =COUNTIFS('Publication Status Tracker NIE'!C:C,C28,'Publication Status Tracker NIE'!O:O,"Q1")+COUNTIFS('Publication Status Tracker NIE'!C:C,C28,'Publication Status Tracker NIE'!O:O,"Q2") -> 4 | K28: =IFERROR(J28/F28*100,0) -> 44.444444 | L28: =COUNTIFS('Publication Status Tracker NIE'!C:C,C28,'Publication Status Tracker NIE'!G:G,"Draft / Work in Progress") -> 2 | M28: =IFERROR(F28/E28*100,0) -> 0 | N28: =IF(H28>=$D$4,"✓ On Target",IF(H28>=$D$4*0.66,"⚠ Approaching",IF(H28>=$D$4*0.33,"↑ Improving","✗ Needs Action"))) -> ✓ On Target
C29: PHY | D29: 8 | E29: =D29*$D$4 -> 0 | F29: =COUNTIFS('Publication Status Tracker NIE'!C:C,C29,'Publication Status Tracker NIE'!G:G,"Published") -> 34 | G29: =COUNTIFS('Publication Status Tracker NIE'!C:C,C29,'Publication Status Tracker NIE'!G:G,"Accepted")+COUNTIFS('Publication Status Tracker NIE'!C:C,C29,'Publication Status Tracker NIE'!G:G,"Under Review")+COUNTIFS('Publication Status Tracker NIE'!C:C,C29,'Publication Status Tracker NIE'!G:G,"Submitted")+COUNTIFS('Publication Status Tracker NIE'!C:C,C29,'Publication Status Tracker NIE'!G:G,"Revision Required") -> 5 | H29: =IFERROR(F29/D29,0) -> 4.25 | I29: =E29-F29 -> -34 | J29: =COUNTIFS('Publication Status Tracker NIE'!C:C,C29,'Publication Status Tracker NIE'!O:O,"Q1")+COUNTIFS('Publication Status Tracker NIE'!C:C,C29,'Publication Status Tracker NIE'!O:O,"Q2") -> 36 | K29: =IFERROR(J29/F29*100,0) -> 105.88235 | L29: =COUNTIFS('Publication Status Tracker NIE'!C:C,C29,'Publication Status Tracker NIE'!G:G,"Draft / Work in Progress") -> 0 | M29: =IFERROR(F29/E29*100,0) -> 0 | N29: =IF(H29>=$D$4,"✓ On Target",IF(H29>=$D$4*0.66,"⚠ Approaching",IF(H29>=$D$4*0.33,"↑ Improving","✗ Needs Action"))) -> ✓ On Target
C30: CHEM | D30: 5 | E30: =D30*$D$4 -> 0 | F30: =COUNTIFS('Publication Status Tracker NIE'!C:C,C30,'Publication Status Tracker NIE'!G:G,"Published") -> 16 | G30: =COUNTIFS('Publication Status Tracker NIE'!C:C,C30,'Publication Status Tracker NIE'!G:G,"Accepted")+COUNTIFS('Publication Status Tracker NIE'!C:C,C30,'Publication Status Tracker NIE'!G:G,"Under Review")+COUNTIFS('Publication Status Tracker NIE'!C:C,C30,'Publication Status Tracker NIE'!G:G,"Submitted")+COUNTIFS('Publication Status Tracker NIE'!C:C,C30,'Publication Status Tracker NIE'!G:G,"Revision Required") -> 7 | H30: =IFERROR(F30/D30,0) -> 3.2 | I30: =E30-F30 -> -16 | J30: =COUNTIFS('Publication Status Tracker NIE'!C:C,C30,'Publication Status Tracker NIE'!O:O,"Q1")+COUNTIFS('Publication Status Tracker NIE'!C:C,C30,'Publication Status Tracker NIE'!O:O,"Q2") -> 19 | K30: =IFERROR(J30/F30*100,0) -> 118.75 | L30: =COUNTIFS('Publication Status Tracker NIE'!C:C,C30,'Publication Status Tracker NIE'!G:G,"Draft / Work in Progress") -> 0 | M30: =IFERROR(F30/E30*100,0) -> 0 | N30: =IF(H30>=$D$4,"✓ On Target",IF(H30>=$D$4*0.66,"⚠ Approaching",IF(H30>=$D$4*0.33,"↑ Improving","✗ Needs Action"))) -> ✓ On Target
C31: TOTAL / AVG | D31: =SUM(D21:D30) -> 196 | E31: =SUM(E21:E30) -> 0 | F31: =SUM(F21:F30) -> 205 | G31: =SUM(G21:G30) -> 245 | H31: =IFERROR(F31/D31,0) -> 1.0459184 | I31: =E31-F31 -> -205 | J31: =SUM(J21:J30) -> 160 | K31: =IFERROR(J31/F31*100,0) -> 78.04878 | L31: =SUM(L21:L30) -> 35 | M31: =IFERROR(F31/E31*100,0) -> 0
B32: ▶ CHARTS — DEPARTMENT PERFORMANCE
B43: ▶ QUALITY TRACKER — SCOPUS QUARTILE BY DEPARTMENT
C44: Department | D44: Total Papers | E44: Q1 | F44: Q2 | G44: Q3 | H44: Q4 | I44: Q1+Q2 | J44: Q1+Q2% | K44: WoS SCI/SCIE | W44: Dept | X44: Published | Y44: Target | Z44: Rate | AA44: Target
C45: =C21 -> CSE | D45: =F21+COUNTIFS('Publication Status Tracker NIE'!C:C,C45,'Publication Status Tracker NIE'!G:G,"Accepted") -> 45 | E45: =COUNTIFS('Publication Status Tracker NIE'!C:C,C45,'Publication Status Tracker NIE'!O:O,"Q1") -> 6 | F45: =COUNTIFS('Publication Status Tracker NIE'!C:C,C45,'Publication Status Tracker NIE'!O:O,"Q2") -> 7 | G45: =COUNTIFS('Publication Status Tracker NIE'!C:C,C45,'Publication Status Tracker NIE'!O:O,"Q3") -> 11 | H45: =COUNTIFS('Publication Status Tracker NIE'!C:C,C45,'Publication Status Tracker NIE'!O:O,"Q4") -> 2 | I45: =E45+F45 -> 13 | J45: =IFERROR((E45+F45)/D45*100,0) -> 28.888889 | K45: =COUNTIFS('Publication Status Tracker NIE'!C:C,C45,'Publication Status Tracker NIE'!P:P,"Yes") -> 14 | W45: =C21 -> CSE | X45: =F21 -> 26 | Y45: =E21 -> 0 | Z45: =H21 -> 0.66666667 | AA45: =$D$4
C46: =C22 -> ISE | D46: =F22+COUNTIFS('Publication Status Tracker NIE'!C:C,C46,'Publication Status Tracker NIE'!G:G,"Accepted") -> 47 | E46: =COUNTIFS('Publication Status Tracker NIE'!C:C,C46,'Publication Status Tracker NIE'!O:O,"Q1") -> 6 | F46: =COUNTIFS('Publication Status Tracker NIE'!C:C,C46,'Publication Status Tracker NIE'!O:O,"Q2") -> 10 | G46: =COUNTIFS('Publication Status Tracker NIE'!C:C,C46,'Publication Status Tracker NIE'!O:O,"Q3") -> 20 | H46: =COUNTIFS('Publication Status Tracker NIE'!C:C,C46,'Publication Status Tracker NIE'!O:O,"Q4") -> 7 | I46: =E46+F46 -> 16 | J46: =IFERROR((E46+F46)/D46*100,0) -> 34.042553 | K46: =COUNTIFS('Publication Status Tracker NIE'!C:C,C46,'Publication Status Tracker NIE'!P:P,"Yes") -> 10 | W46: =C22 -> ISE | X46: =F22 -> 30 | Y46: =E22 -> 0 | Z46: =H22 -> 1.0344828 | AA46: =$D$4
C47: =C23 -> ECE | D47: =F23+COUNTIFS('Publication Status Tracker NIE'!C:C,C47,'Publication Status Tracker NIE'!G:G,"Accepted") -> 43 | E47: =COUNTIFS('Publication Status Tracker NIE'!C:C,C47,'Publication Status Tracker NIE'!O:O,"Q1") -> 12 | F47: =COUNTIFS('Publication Status Tracker NIE'!C:C,C47,'Publication Status Tracker NIE'!O:O,"Q2") -> 21 | G47: =COUNTIFS('Publication Status Tracker NIE'!C:C,C47,'Publication Status Tracker NIE'!O:O,"Q3") -> 10 | H47: =COUNTIFS('Publication Status Tracker NIE'!C:C,C47,'Publication Status Tracker NIE'!O:O,"Q4") -> 4 | I47: =E47+F47 -> 33 | J47: =IFERROR((E47+F47)/D47*100,0) -> 76.744186 | K47: =COUNTIFS('Publication Status Tracker NIE'!C:C,C47,'Publication Status Tracker NIE'!P:P,"Yes") -> 18 | W47: =C23 -> ECE | X47: =F23 -> 29 | Y47: =E23 -> 0 | Z47: =H23 -> 1.2608696 | AA47: =$D$4
C48: =C24 -> MECH | D48: =F24+COUNTIFS('Publication Status Tracker NIE'!C:C,C48,'Publication Status Tracker NIE'!G:G,"Accepted") -> 42 | E48: =COUNTIFS('Publication Status Tracker NIE'!C:C,C48,'Publication Status Tracker NIE'!O:O,"Q1") -> 7 | F48: =COUNTIFS('Publication Status Tracker NIE'!C:C,C48,'Publication Status Tracker NIE'!O:O,"Q2") -> 10 | G48: =COUNTIFS('Publication Status Tracker NIE'!C:C,C48,'Publication Status Tracker NIE'!O:O,"Q3") -> 13 | H48: =COUNTIFS('Publication Status Tracker NIE'!C:C,C48,'Publication Status Tracker NIE'!O:O,"Q4") -> 20 | I48: =E48+F48 -> 17 | J48: =IFERROR((E48+F48)/D48*100,0) -> 40.47619 | K48: =COUNTIFS('Publication Status Tracker NIE'!C:C,C48,'Publication Status Tracker NIE'!P:P,"Yes") -> 16 | W48: =C24 -> MECH | X48: =F24 -> 21 | Y48: =E24 -> 0 | Z48: =H24 -> 0.67741935 | AA48: =$D$4
C49: =C25 -> CIVIL | D49: =F25+COUNTIFS('Publication Status Tracker NIE'!C:C,C49,'Publication Status Tracker NIE'!G:G,"Accepted") -> 31 | E49: =COUNTIFS('Publication Status Tracker NIE'!C:C,C49,'Publication Status Tracker NIE'!O:O,"Q1") -> 6 | F49: =COUNTIFS('Publication Status Tracker NIE'!C:C,C49,'Publication Status Tracker NIE'!O:O,"Q2") -> 12 | G49: =COUNTIFS('Publication Status Tracker NIE'!C:C,C49,'Publication Status Tracker NIE'!O:O,"Q3") -> 21 | H49: =COUNTIFS('Publication Status Tracker NIE'!C:C,C49,'Publication Status Tracker NIE'!O:O,"Q4") -> 1 | I49: =E49+F49 -> 18 | J49: =IFERROR((E49+F49)/D49*100,0) -> 58.064516 | K49: =COUNTIFS('Publication Status Tracker NIE'!C:C,C49,'Publication Status Tracker NIE'!P:P,"Yes") -> 17 | W49: =C25 -> CIVIL | X49: =F25 -> 12 | Y49: =E25 -> 0 | Z49: =H25 -> 0.54545455 | AA49: =$D$4
C50: =C26 -> EEE | D50: =F26+COUNTIFS('Publication Status Tracker NIE'!C:C,C50,'Publication Status Tracker NIE'!G:G,"Accepted") -> 21 | E50: =COUNTIFS('Publication Status Tracker NIE'!C:C,C50,'Publication Status Tracker NIE'!O:O,"Q1") -> 1 | F50: =COUNTIFS('Publication Status Tracker NIE'!C:C,C50,'Publication Status Tracker NIE'!O:O,"Q2") -> 3 | G50: =COUNTIFS('Publication Status Tracker NIE'!C:C,C50,'Publication Status Tracker NIE'!O:O,"Q3") -> 4 | H50: =COUNTIFS('Publication Status Tracker NIE'!C:C,C50,'Publication Status Tracker NIE'!O:O,"Q4") -> 7 | I50: =E50+F50 -> 4 | J50: =IFERROR((E50+F50)/D50*100,0) -> 19.047619 | K50: =COUNTIFS('Publication Status Tracker NIE'!C:C,C50,'Publication Status Tracker NIE'!P:P,"Yes") -> 9 | W50: =C26 -> EEE | X50: =F26 -> 9 | Y50: =E26 -> 0 | Z50: =H26 -> 0.6 | AA50: =$D$4
C51: =C27 -> MCA | D51: =F27+COUNTIFS('Publication Status Tracker NIE'!C:C,C51,'Publication Status Tracker NIE'!G:G,"Accepted") -> 20 | E51: =COUNTIFS('Publication Status Tracker NIE'!C:C,C51,'Publication Status Tracker NIE'!O:O,"Q1") -> 0 | F51: =COUNTIFS('Publication Status Tracker NIE'!C:C,C51,'Publication Status Tracker NIE'!O:O,"Q2") -> 0 | G51: =COUNTIFS('Publication Status Tracker NIE'!C:C,C51,'Publication Status Tracker NIE'!O:O,"Q3") -> 0 | H51: =COUNTIFS('Publication Status Tracker NIE'!C:C,C51,'Publication Status Tracker NIE'!O:O,"Q4") -> 2 | I51: =E51+F51 -> 0 | J51: =IFERROR((E51+F51)/D51*100,0) -> 0 | K51: =COUNTIFS('Publication Status Tracker NIE'!C:C,C51,'Publication Status Tracker NIE'!P:P,"Yes") -> 0 | W51: =C27 -> MCA | X51: =F27 -> 19 | Y51: =E27 -> 0 | Z51: =H27 -> 1.5833333 | AA51: =$D$4
C52: =C28 -> MATHS | D52: =F28+COUNTIFS('Publication Status Tracker NIE'!C:C,C52,'Publication Status Tracker NIE'!G:G,"Accepted") -> 15 | E52: =COUNTIFS('Publication Status Tracker NIE'!C:C,C52,'Publication Status Tracker NIE'!O:O,"Q1") -> 1 | F52: =COUNTIFS('Publication Status Tracker NIE'!C:C,C52,'Publication Status Tracker NIE'!O:O,"Q2") -> 3 | G52: =COUNTIFS('Publication Status Tracker NIE'!C:C,C52,'Publication Status Tracker NIE'!O:O,"Q3") -> 14 | H52: =COUNTIFS('Publication Status Tracker NIE'!C:C,C52,'Publication Status Tracker NIE'!O:O,"Q4") -> 3 | I52: =E52+F52 -> 4 | J52: =IFERROR((E52+F52)/D52*100,0) -> 26.666667 | K52: =COUNTIFS('Publication Status Tracker NIE'!C:C,C52,'Publication Status Tracker NIE'!P:P,"Yes") -> 8 | W52: =C28 -> MATHS | X52: =F28 -> 9 | Y52: =E28 -> 0 | Z52: =H28 -> 0.75 | AA52: =$D$4
C53: =C29 -> PHY | D53: =F29+COUNTIFS('Publication Status Tracker NIE'!C:C,C53,'Publication Status Tracker NIE'!G:G,"Accepted") -> 35 | E53: =COUNTIFS('Publication Status Tracker NIE'!C:C,C53,'Publication Status Tracker NIE'!O:O,"Q1") -> 7 | F53: =COUNTIFS('Publication Status Tracker NIE'!C:C,C53,'Publication Status Tracker NIE'!O:O,"Q2") -> 29 | G53: =COUNTIFS('Publication Status Tracker NIE'!C:C,C53,'Publication Status Tracker NIE'!O:O,"Q3") -> 1 | H53: =COUNTIFS('Publication Status Tracker NIE'!C:C,C53,'Publication Status Tracker NIE'!O:O,"Q4") -> 2 | I53: =E53+F53 -> 36 | J53: =IFERROR((E53+F53)/D53*100,0) -> 102.85714 | K53: =COUNTIFS('Publication Status Tracker NIE'!C:C,C53,'Publication Status Tracker NIE'!P:P,"Yes") -> 35 | W53: =C29 -> PHY | X53: =F29 -> 34 | Y53: =E29 -> 0 | Z53: =H29 -> 4.25 | AA53: =$D$4
C54: =C30 -> CHEM | D54: =F30+COUNTIFS('Publication Status Tracker NIE'!C:C,C54,'Publication Status Tracker NIE'!G:G,"Accepted") -> 19 | E54: =COUNTIFS('Publication Status Tracker NIE'!C:C,C54,'Publication Status Tracker NIE'!O:O,"Q1") -> 16 | F54: =COUNTIFS('Publication Status Tracker NIE'!C:C,C54,'Publication Status Tracker NIE'!O:O,"Q2") -> 3 | G54: =COUNTIFS('Publication Status Tracker NIE'!C:C,C54,'Publication Status Tracker NIE'!O:O,"Q3") -> 1 | H54: =COUNTIFS('Publication Status Tracker NIE'!C:C,C54,'Publication Status Tracker NIE'!O:O,"Q4") -> 1 | I54: =E54+F54 -> 19 | J54: =IFERROR((E54+F54)/D54*100,0) -> 100 | K54: =COUNTIFS('Publication Status Tracker NIE'!C:C,C54,'Publication Status Tracker NIE'!P:P,"Yes") -> 15 | W54: =C30 -> CHEM | X54: =F30 -> 16 | Y54: =E30 -> 0 | Z54: =H30 -> 3.2 | AA54: =$D$4
C55: TOTAL | D55: =SUM(D45:D54) -> 318 | E55: =SUM(E45:E54) -> 62 | F55: =SUM(F45:F54) -> 98 | G55: =SUM(G45:G54) -> 95 | H55: =SUM(H45:H54) -> 49 | I55: =SUM(I45:I54) -> 160 | J55: =IFERROR(I55/D55*100,0) -> 50.314465 | K55: =SUM(K45:K54) -> 142
B58: Notes: • Target is set in cell D4 (currently 3 publications/faculty/year) • Pipeline = Accepted + Under Review + Submitted + Revision Required • Data auto-updates from Publication Status Tracker sheet • Q1+Q2 % based on published papers only

Sheet Dept & Faculty
B2: Department | C2: Professors | D2: Assoc. Profs | E2: Asst. Profs | F2: On Contract | G2: Total
B3: CSE | C3: 5 | D3: 4 | E3: 30 | F3: 0 | G3: =SUM(C3:F3) -> 39
B4: ISE | C4: 5 | D4: 6 | E4: 18 | F4: 0 | G4: =SUM(C4:F4) -> 29
B5: MECH | C5: 3 | D5: 3 | E5: 23 | F5: 2 | G5: =SUM(C5:F5) -> 31
B6: ECE | C6: 0 | D6: 7 | E6: 12 | F6: 4 | G6: =SUM(C6:F6) -> 23
B7: CIVIL | C7: 2 | D7: 3 | E7: 9 | F7: 7 | G7: =SUM(C7:F7) -> 21
B8: EEE | C8: 2 | D8: 4 | E8: 5 | F8: 10 | G8: =SUM(C8:F8) -> 21
B9: MCA | C9: 1 | D9: 2 | E9: 1 | F9: 6 | G9: =SUM(C9:F9) -> 10
B10: MATHS | C10: 1 | D10: 3 | E10: 3 | F10: 5 | G10: =SUM(C10:F10) -> 12
B11: PHY | C11: 1 | D11: 2 | E11: 2 | F11: 3 | G11: =SUM(C11:F11) -> 8
B12: CHEM | C12: 0 | D12: 2 | E12: 3 | F12: 4 | G12: =SUM(C12:F12) -> 9
B13: TOTAL | C13: =SUM(C3:C12) -> 20 | D13: =SUM(D3:D12) -> 36 | E13: =SUM(E3:E12) -> 106 | F13: =SUM(F3:F12) -> 41 | G13: =SUM(G3:G12) -> 203
